LICENSE
README.md
setup.cfg
setup.py
bear/__init__.py
bear/graph.py
bear/pipeline.py
bear/plotting.py
bear.egg-info/PKG-INFO
bear.egg-info/SOURCES.txt
bear.egg-info/dependency_links.txt
bear.egg-info/not-zip-safe
bear.egg-info/requires.txt
bear.egg-info/top_level.txt
tests/__init__.py
tests/test.py
tests/test_plot.py