Metadata-Version: 2.1
Name: bear
Version: 2.1
Summary: asynchronous parallelization pipeline
Home-page: https://github.com/kouroshparsa/bear
Author: Kourosh Parsa
Author-email: kouroshtheking@gmail.com
License: GNU
Download-URL: https://github.com/kouroshparsa/bear/packages/2.1
Platform: all
Classifier: Programming Language :: Python
License-File: LICENSE
